setup.py
flask_simple_login/__init__.py
flask_simple_login/simple_login.py
flask_simple_login.egg-info/PKG-INFO
flask_simple_login.egg-info/SOURCES.txt
flask_simple_login.egg-info/dependency_links.txt
flask_simple_login.egg-info/top_level.txt
flask_simple_login.egg-info/zip-safe