Metadata-Version: 1.0
Name: flask-simple-login
Version: 0.0.1
Summary: Easily turn your python data into a flot graph in a static html file.
Home-page: https://github.com/JesseAldridge/flask_simple_login
Author: Jesse Aldridge
Author-email: JesseAldridge@gmail.com
License: MIT
Keywords: flask auth login
Platform: UNKNOWN
